uniparser_turoyo/__init__.py
uniparser_turoyo/__main__.py
uniparser_turoyo/analyzer.py
uniparser_turoyo/data_nodiacritics/__init__.py
uniparser_turoyo/data_nodiacritics/lexemes.txt
uniparser_turoyo/data_nodiacritics/paradigms.txt
uniparser_turoyo/data_strict/__init__.py
uniparser_turoyo/data_strict/lexemes.txt
uniparser_turoyo/data_strict/paradigms.txt
uniparser_turoyo-1.1.2.dist-info/LICENSE
uniparser_turoyo-1.1.2.dist-info/METADATA
uniparser_turoyo-1.1.2.dist-info/WHEEL
uniparser_turoyo-1.1.2.dist-info/top_level.txt
uniparser_turoyo-1.1.2.dist-info/RECORD
