Metadata-Version: 2.1
Name: uniparser-turoyo
Version: 1.1.2
Summary: Rule-based morphological analysis for Turoyo
Home-page: https://github.com/margisk/uniparser-grammar-turoyo
Author: Timofey Arkhangelskiy
Author-email: timarkh@gmail.com
Project-URL: Bug Tracker, https://github.com/margisk/uniparser-grammar-turoyo/issues
Classifier: Programming Language :: Python :: 3
Classifier: License :: OSI Approved :: MIT License
Classifier: Operating System :: OS Independent
Classifier: Intended Audience :: Science/Research
Classifier: Topic :: Text Processing :: Linguistic
Requires-Python: >=3.7
License-File: LICENSE
Requires-Dist: uniparser-morph (>=2.4.1)
Requires-Dist: importlib-resources
